DIYables_MicroPython_Joystick/DIYables_MicroPython_Joystick.py
DIYables_MicroPython_Joystick/__init__.py
DIYables_MicroPython_Joystick-0.1.0.dist-info/LICENSE
DIYables_MicroPython_Joystick-0.1.0.dist-info/METADATA
DIYables_MicroPython_Joystick-0.1.0.dist-info/WHEEL
DIYables_MicroPython_Joystick-0.1.0.dist-info/top_level.txt
DIYables_MicroPython_Joystick-0.1.0.dist-info/RECORD
